{
  "miniprogramRoot": "miniprogram/",
  "cloudfunctionRoot": "cloudfunctions/",
  "setting": {
    "urlCheck": false,
    "es6": true,
    "enhance": true,
    "postcss": true,
    "preloadBackgroundData": false,
    "minified": true,
    "newFeature": true,
    "coverView": true,
    "nodeModules": false,
    "autoAudits": false,
    "showShadowRootInWxmlPanel": true,
    "scopeDataCheck": false,
    "uglifyFileName": false,
    "checkInvalidKey": true,
    "checkSiteMap": true,
    "uploadWithSourceMap": true,
    "compileHotReLoad": false,
    "useMultiFrameRuntime": true,
    "useApiHook": true,
    "useApiHostProcess": true,
    "babelSetting": {
      "ignore": [],
      "disablePlugins": [],
      "outputPath": ""
    },
    "enableEngineNative": false,
    "bundle": false,
    "useIsolateContext": true,
    "useCompilerModule": true,
    "userConfirmedUseCompilerModuleSwitch": false,
    "userConfirmedBundleSwitch": false,
    "packNpmManually": false,
    "packNpmRelationList": [],
    "minifyWXSS": true
  },
  "appid": "wx706a781c6ef67d0b",
  "projectname": "cloud-music",
  "libVersion": "2.14.1",
  "cloudfunctionTemplateRoot": "cloudfunctionTemplate",
  "condition": {
    "plugin": {
      "list": []
    },
    "game": {
      "list": []
    },
    "gamePlugin": {
      "list": []
    },
    "miniprogram": {
      "list": [
        {
          "id": -1,
          "name": "db guide",
          "pathName": "pages/databaseGuide/databaseGuide",
          "query": ""
        },
        {
          "name": "test",
          "pathName": "pages/test/test",
          "query": "",
          "scene": null
        },
        {
          "name": "musiclist",
          "pathName": "pages/musiclist/musiclist",
          "query": "playlistId=104565668",
          "scene": null
        },
        {
          "name": "player",
          "pathName": "pages/player/player",
          "query": "musicId=247187&index=0",
          "scene": null
        },
        {
          "name": "profile",
          "pathName": "pages/profile/profile",
          "query": "musicId=247187&index=0",
          "scene": null
        }
      ]
    }
  }
}